{
  "scriptId": "431",
  "url": "file:///C:/Users/pyanq/AppData/Local/deno/npm/registry.npmjs.org/mongodb/6.10.0/lib/operations/indexes.js",
  "functions": [
    {
      "functionName": "",
      "ranges": [
        {
          "startOffset": 0,
          "endOffset": 7228,
          "count": 1
        }
      ],
      "isBlockCoverage": true
    },
    {
      "functionName": "",
      "ranges": [
        {
          "startOffset": 1,
          "endOffset": 7227,
          "count": 1
        }
      ],
      "isBlockCoverage": true
    },
    {
      "functionName": "",
      "ranges": [
        {
          "startOffset": 214,
          "endOffset": 7221,
          "count": 1
        }
      ],
      "isBlockCoverage": true
    },
    {
      "functionName": "isIndexDirection",
      "ranges": [
        {
          "startOffset": 1152,
          "endOffset": 1293,
          "count": 0
        }
      ],
      "isBlockCoverage": false
    },
    {
      "functionName": "isSingleIndexTuple",
      "ranges": [
        {
          "startOffset": 1294,
          "endOffset": 1401,
          "count": 0
        }
      ],
      "isBlockCoverage": false
    },
    {
      "functionName": "constructIndexDescriptionMap",
      "ranges": [
        {
          "startOffset": 1544,
          "endOffset": 2361,
          "count": 0
        }
      ],
      "isBlockCoverage": false
    },
    {
      "functionName": "resolveIndexDescription",
      "ranges": [
        {
          "startOffset": 2561,
          "endOffset": 2965,
          "count": 0
        }
      ],
      "isBlockCoverage": false
    },
    {
      "functionName": "CreateIndexesOperation",
      "ranges": [
        {
          "startOffset": 3053,
          "endOffset": 3742,
          "count": 0
        }
      ],
      "isBlockCoverage": false
    },
    {
      "functionName": "fromIndexDescriptionArray",
      "ranges": [
        {
          "startOffset": 3754,
          "endOffset": 3914,
          "count": 0
        }
      ],
      "isBlockCoverage": false
    },
    {
      "functionName": "fromIndexSpecification",
      "ranges": [
        {
          "startOffset": 3926,
          "endOffset": 4206,
          "count": 0
        }
      ],
      "isBlockCoverage": false
    },
    {
      "functionName": "get commandName",
      "ranges": [
        {
          "startOffset": 4211,
          "endOffset": 4268,
          "count": 0
        }
      ],
      "isBlockCoverage": false
    },
    {
      "functionName": "execute",
      "ranges": [
        {
          "startOffset": 4273,
          "endOffset": 5100,
          "count": 0
        }
      ],
      "isBlockCoverage": false
    },
    {
      "functionName": "DropIndexOperation",
      "ranges": [
        {
          "startOffset": 5243,
          "endOffset": 5442,
          "count": 0
        }
      ],
      "isBlockCoverage": false
    },
    {
      "functionName": "get commandName",
      "ranges": [
        {
          "startOffset": 5447,
          "endOffset": 5502,
          "count": 0
        }
      ],
      "isBlockCoverage": false
    },
    {
      "functionName": "execute",
      "ranges": [
        {
          "startOffset": 5507,
          "endOffset": 5702,
          "count": 0
        }
      ],
      "isBlockCoverage": false
    },
    {
      "functionName": "ListIndexesOperation",
      "ranges": [
        {
          "startOffset": 5839,
          "endOffset": 6055,
          "count": 0
        }
      ],
      "isBlockCoverage": false
    },
    {
      "functionName": "get commandName",
      "ranges": [
        {
          "startOffset": 6060,
          "endOffset": 6115,
          "count": 0
        }
      ],
      "isBlockCoverage": false
    },
    {
      "functionName": "execute",
      "ranges": [
        {
          "startOffset": 6120,
          "endOffset": 6773,
          "count": 0
        }
      ],
      "isBlockCoverage": false
    }
  ]
}