{
  "scriptId": "480",
  "url": "file:///C:/Users/pyanq/AppData/Local/deno/npm/registry.npmjs.org/mongodb/6.10.0/lib/cmap/handshake/client_metadata.js",
  "functions": [
    {
      "functionName": "",
      "ranges": [
        {
          "startOffset": 0,
          "endOffset": 9207,
          "count": 1
        }
      ],
      "isBlockCoverage": true
    },
    {
      "functionName": "",
      "ranges": [
        {
          "startOffset": 1,
          "endOffset": 9206,
          "count": 1
        }
      ],
      "isBlockCoverage": true
    },
    {
      "functionName": "",
      "ranges": [
        {
          "startOffset": 214,
          "endOffset": 9200,
          "count": 1
        }
      ],
      "isBlockCoverage": true
    },
    {
      "functionName": "LimitedSizeDocument",
      "ranges": [
        {
          "startOffset": 836,
          "endOffset": 1010,
          "count": 7
        }
      ],
      "isBlockCoverage": true
    },
    {
      "functionName": "ifItFitsItSits",
      "ranges": [
        {
          "startOffset": 1090,
          "endOffset": 1598,
          "count": 28
        },
        {
          "startOffset": 1450,
          "endOffset": 1487,
          "count": 0
        }
      ],
      "isBlockCoverage": true
    },
    {
      "functionName": "toObject",
      "ranges": [
        {
          "startOffset": 1603,
          "endOffset": 1845,
          "count": 7
        }
      ],
      "isBlockCoverage": true
    },
    {
      "functionName": "makeClientMetadata",
      "ranges": [
        {
          "startOffset": 2245,
          "endOffset": 4511,
          "count": 7
        },
        {
          "startOffset": 2559,
          "endOffset": 2623,
          "count": 0
        },
        {
          "startOffset": 2827,
          "endOffset": 2845,
          "count": 0
        },
        {
          "startOffset": 2894,
          "endOffset": 2931,
          "count": 0
        },
        {
          "startOffset": 3025,
          "endOffset": 3168,
          "count": 0
        },
        {
          "startOffset": 3238,
          "endOffset": 3297,
          "count": 0
        },
        {
          "startOffset": 3365,
          "endOffset": 3500,
          "count": 0
        },
        {
          "startOffset": 3830,
          "endOffset": 4066,
          "count": 0
        },
        {
          "startOffset": 4126,
          "endOffset": 4469,
          "count": 0
        }
      ],
      "isBlockCoverage": true
    },
    {
      "functionName": "getContainerMetadata",
      "ranges": [
        {
          "startOffset": 4548,
          "endOffset": 5038,
          "count": 7
        },
        {
          "startOffset": 4850,
          "endOffset": 4856,
          "count": 0
        },
        {
          "startOffset": 4892,
          "endOffset": 4929,
          "count": 0
        },
        {
          "startOffset": 4960,
          "endOffset": 5006,
          "count": 0
        }
      ],
      "isBlockCoverage": true
    },
    {
      "functionName": "addContainerMetadata",
      "ranges": [
        {
          "startOffset": 5175,
          "endOffset": 6106,
          "count": 7
        },
        {
          "startOffset": 5376,
          "endOffset": 5494,
          "count": 0
        },
        {
          "startOffset": 5591,
          "endOffset": 6105,
          "count": 0
        }
      ],
      "isBlockCoverage": true
    },
    {
      "functionName": "getFAASEnv",
      "ranges": [
        {
          "startOffset": 6196,
          "endOffset": 8417,
          "count": 7
        },
        {
          "startOffset": 7002,
          "endOffset": 7032,
          "count": 0
        },
        {
          "startOffset": 7034,
          "endOffset": 7204,
          "count": 0
        },
        {
          "startOffset": 7223,
          "endOffset": 7269,
          "count": 0
        },
        {
          "startOffset": 7271,
          "endOffset": 7662,
          "count": 0
        },
        {
          "startOffset": 7683,
          "endOffset": 7727,
          "count": 0
        },
        {
          "startOffset": 7729,
          "endOffset": 7803,
          "count": 0
        },
        {
          "startOffset": 7822,
          "endOffset": 7868,
          "count": 0
        },
        {
          "startOffset": 7870,
          "endOffset": 8398,
          "count": 0
        }
      ],
      "isBlockCoverage": true
    },
    {
      "functionName": "getRuntimeInfo",
      "ranges": [
        {
          "startOffset": 8684,
          "endOffset": 9154,
          "count": 7
        },
        {
          "startOffset": 8830,
          "endOffset": 8847,
          "count": 0
        },
        {
          "startOffset": 8909,
          "endOffset": 9153,
          "count": 0
        }
      ],
      "isBlockCoverage": true
    }
  ]
}